CONTRIBUTORS.txt
README.txt
setup.cfg
setup.py
docs/HISTORY.txt
docs/INSTALL.txt
docs/LICENSE.GPL
docs/LICENSE.txt
slc/__init__.py
slc.mindmap.egg-info/PKG-INFO
slc.mindmap.egg-info/SOURCES.txt
slc.mindmap.egg-info/dependency_links.txt
slc.mindmap.egg-info/entry_points.txt
slc.mindmap.egg-info/namespace_packages.txt
slc.mindmap.egg-info/not-zip-safe
slc.mindmap.egg-info/requires.txt
slc.mindmap.egg-info/top_level.txt
slc/mindmap/__init__.py
slc/mindmap/config.py
slc/mindmap/configure.zcml
slc/mindmap/descriptors.py
slc/mindmap/interfaces.py
slc/mindmap/setuphandlers.py
slc/mindmap/tests.py
slc/mindmap/version.txt
slc/mindmap/browser/__init__.py
slc/mindmap/browser/config.py
slc/mindmap/browser/configure.zcml
slc/mindmap/browser/interfaces.py
slc/mindmap/browser/mindmap.py
slc/mindmap/browser/viewlets.py
slc/mindmap/browser/templates/mindmap.pt
slc/mindmap/browser/templates/preview.pt
slc/mindmap/i18n/slc.mindmap-plone-en.po
slc/mindmap/profiles/default/actionicons.xml
slc/mindmap/profiles/default/controlpanel.xml
slc/mindmap/profiles/default/import_steps.xml
slc/mindmap/profiles/default/metadata.xml
slc/mindmap/profiles/default/slc_mindmap_marker.txt
slc/mindmap/tests/Plone_API.mmap
slc/mindmap/tests/__init__.py
slc/mindmap/tests/empty.mmap
slc/mindmap/tests/testMindMapSaveFromEditor.py
slc/mindmap/tests/testMindMeisterAPI.py