Metadata-Version: 1.0
Name: slc.mindmap
Version: 1.0beta1
Summary: Add editing, viewing and exporting support for mindmaps in Plone via an embedded mindmeister.com editor.
Home-page: http://plone.org/products/slc.mindmap
Author: J-C Brand, Syslab.com GmbH
Author-email: brand@syslab.com
License: GPL
Keywords: mindmeister mindmap syslab slc
Platform: UNKNOWN
Classifier: Framework :: Plone
Classifier: Programming Language :: Python
Classifier: Topic :: Software Development :: Libraries :: Python Modules
